LICENSE
MANIFEST.in
README.md
setup.cfg
setup.py
PuntoPagos.egg-info/PKG-INFO
PuntoPagos.egg-info/SOURCES.txt
PuntoPagos.egg-info/dependency_links.txt
PuntoPagos.egg-info/entry_points.txt
PuntoPagos.egg-info/top_level.txt
PuntoPagos.egg-info/zip-safe
docs/Makefile
docs/make.bat
docs/build/doctrees/environment.pickle
docs/build/doctrees/gentingstarted.doctree
docs/build/doctrees/getingstarted.doctree
docs/build/doctrees/gettingstarted.doctree
docs/build/doctrees/index.doctree
docs/build/doctrees/restapi.doctree
docs/build/html/.buildinfo
docs/build/html/genindex.html
docs/build/html/gentingstarted.html
docs/build/html/getingstarted.html
docs/build/html/gettingstarted.html
docs/build/html/index.html
docs/build/html/objects.inv
docs/build/html/py-modindex.html
docs/build/html/restapi.html
docs/build/html/search.html
docs/build/html/searchindex.js
docs/build/html/_modules/index.html
docs/build/html/_modules/puntopagos.html
docs/build/html/_sources/gentingstarted.txt
docs/build/html/_sources/getingstarted.txt
docs/build/html/_sources/gettingstarted.txt
docs/build/html/_sources/index.txt
docs/build/html/_sources/restapi.txt
docs/build/html/_static/ajax-loader.gif
docs/build/html/_static/basic.css
docs/build/html/_static/comment-bright.png
docs/build/html/_static/comment-close.png
docs/build/html/_static/comment.png
docs/build/html/_static/default.css
docs/build/html/_static/doctools.js
docs/build/html/_static/down-pressed.png
docs/build/html/_static/down.png
docs/build/html/_static/file.png
docs/build/html/_static/jquery.js
docs/build/html/_static/minus.png
docs/build/html/_static/plus.png
docs/build/html/_static/pygments.css
docs/build/html/_static/searchtools.js
docs/build/html/_static/sidebar.js
docs/build/html/_static/underscore.js
docs/build/html/_static/up-pressed.png
docs/build/html/_static/up.png
docs/build/html/_static/websupport.js
docs/source/conf.py
docs/source/index.rst
docs/source/index.rst~
docs/source/restapi.rst
puntopagos/__init__.py
puntopagos/notification.py
puntopagos/request.py
puntopagos/response.py
puntopagos/util.py