Metadata-Version: 1.1
Name: PuntoPagos
Version: 0.2.0dev
Summary: Punto Pagos REST API implementation
Home-page: http://desarrollo.witoi.com
Author: Pedro Buron, Alejandro Varas
Author-email: pedro@witoi.com, alejandro@witoi.com
License: GPLv3
Keywords: puntopagos,witoi,e-commerce
Platform: UNKNOWN
Classifier: Development Status :: 4 - Beta
Classifier: Intended Audience :: Developers
Classifier: License :: OSI Approved :: GNU General Public License v3 (GPLv3)
